COERbuoyOne/__init__.py
COERbuoyOne/__main__.py
COERbuoyOne/benchmark.py
COERbuoyOne/cert_raw.svg
COERbuoyOne/benchmark/.gitignore
COERbuoyOne/benchmark/benchmark0.csv
COERbuoyOne/benchmark/benchmark1.csv
COERbuoyOne/benchmark/benchmark10.csv
COERbuoyOne/benchmark/benchmark11.csv
COERbuoyOne/benchmark/benchmark12.csv
COERbuoyOne/benchmark/benchmark13.csv
COERbuoyOne/benchmark/benchmark14.csv
COERbuoyOne/benchmark/benchmark15.csv
COERbuoyOne/benchmark/benchmark16.csv
COERbuoyOne/benchmark/benchmark17.csv
COERbuoyOne/benchmark/benchmark18.csv
COERbuoyOne/benchmark/benchmark19.csv
COERbuoyOne/benchmark/benchmark2.csv
COERbuoyOne/benchmark/benchmark20.csv
COERbuoyOne/benchmark/benchmark21.csv
COERbuoyOne/benchmark/benchmark22.csv
COERbuoyOne/benchmark/benchmark23.csv
COERbuoyOne/benchmark/benchmark3.csv
COERbuoyOne/benchmark/benchmark4.csv
COERbuoyOne/benchmark/benchmark5.csv
COERbuoyOne/benchmark/benchmark6.csv
COERbuoyOne/benchmark/benchmark7.csv
COERbuoyOne/benchmark/benchmark8.csv
COERbuoyOne/benchmark/benchmark9.csv
COERbuoyOne/coerbuoy1/dynamics.py
COERbuoyOne/coerbuoy1/floater.txt
COERbuoyOne/coerbuoy1/BEM/h_-0.5_p_0/results/CA.dat
COERbuoyOne/coerbuoy1/BEM/h_-0.5_p_0/results/CM.dat
COERbuoyOne/coerbuoy1/BEM/h_-0.5_p_0/results/DiffractionForce.tec
COERbuoyOne/coerbuoy1/BEM/h_-0.5_p_0/results/ExcitationForce.tec
COERbuoyOne/coerbuoy1/BEM/h_-0.5_p_0/results/FKForce.dat
COERbuoyOne/coerbuoy1/BEM/h_-0.5_p_0/results/FKForce.tec
COERbuoyOne/coerbuoy1/BEM/h_-0.5_p_0/results/Fe.dat
COERbuoyOne/coerbuoy1/BEM/h_-0.5_p_0/results/Forces.dat
COERbuoyOne/coerbuoy1/BEM/h_-0.5_p_0/results/IRF.tec
COERbuoyOne/coerbuoy1/BEM/h_-0.5_p_0/results/RadiationCoefficients.tec
COERbuoyOne/coerbuoy1/BEM/h_-0.5_p_0/results/index.dat
COERbuoyOne/coerbuoy1/BEM/h_-1.5_p_0/results/CA.dat
COERbuoyOne/coerbuoy1/BEM/h_-1.5_p_0/results/CM.dat
COERbuoyOne/coerbuoy1/BEM/h_-1.5_p_0/results/DiffractionForce.tec
COERbuoyOne/coerbuoy1/BEM/h_-1.5_p_0/results/ExcitationForce.tec
COERbuoyOne-0.3.0.dist-info/LICENSE.txt
COERbuoyOne-0.3.0.dist-info/METADATA
COERbuoyOne-0.3.0.dist-info/WHEEL
COERbuoyOne-0.3.0.dist-info/top_level.txt
COERbuoyOne-0.3.0.dist-info/RECORD
