Metadata-Version: 2.1
Name: COERbuoyOne
Version: 0.3.0
Summary: A realistic benchmark for Wave Enegery Converter controllers
Home-page: http://coerbuoy.maynoothuniversity.ie
Author: Simon H. Thomas
Author-email: simon.thomas.2021@mumail.ie
License: LICENSE.txt
Platform: UNKNOWN
License-File: LICENSE.txt
Requires-Dist: numpy
Requires-Dist: scipy
Requires-Dist: pandas
Requires-Dist: COERbuoy (>=0.3)
